scientific_survey/__init__.py
scientific_survey/actions.py
scientific_survey/admin.py
scientific_survey/apps.py
scientific_survey/decorators.py
scientific_survey/forms.py
scientific_survey/runtests.py
scientific_survey/settings.py
scientific_survey/signals.py
scientific_survey/urls.py
scientific_survey/widgets.py
scientific_survey/__pycache__/__init__.cpython-310.pyc
scientific_survey/__pycache__/actions.cpython-310.pyc
scientific_survey/__pycache__/admin.cpython-310.pyc
scientific_survey/__pycache__/apps.cpython-310.pyc
scientific_survey/__pycache__/decorators.cpython-310.pyc
scientific_survey/__pycache__/forms.cpython-310.pyc
scientific_survey/__pycache__/settings.cpython-310.pyc
scientific_survey/__pycache__/signals.cpython-310.pyc
scientific_survey/__pycache__/urls.cpython-310.pyc
scientific_survey/__pycache__/widgets.cpython-310.pyc
scientific_survey/exporter/__init__.py
scientific_survey/exporter/survey2x.py
scientific_survey/exporter/__pycache__/__init__.cpython-310.pyc
scientific_survey/exporter/__pycache__/survey2x.cpython-310.pyc
scientific_survey/exporter/json/__init__.py
scientific_survey/exporter/json/survey2json.py
scientific_survey/exporter/json/__pycache__/__init__.cpython-310.pyc
scientific_survey/exporter/json/__pycache__/survey2json.cpython-310.pyc
scientific_survey/importer/__init__.py
scientific_survey/importer/yaml2survey.py
scientific_survey/importer/__pycache__/__init__.cpython-310.pyc
scientific_survey/importer/__pycache__/json2survey.cpython-310.pyc
scientific_survey/importer/__pycache__/yaml2survey.cpython-310.pyc
scientific_survey/locale/de/LC_MESSAGES/django.mo
scientific_survey/locale/de/LC_MESSAGES/django.po
scientific_survey/locale/es/LC_MESSAGES/django.mo
scientific_survey/locale/es/LC_MESSAGES/django.po
scientific_survey/locale/fr/LC_MESSAGES/django.mo
scientific_survey/locale/fr/LC_MESSAGES/django.po
scientific_survey/locale/id/LC_MESSAGES/django.mo
scientific_survey/locale/id/LC_MESSAGES/django.po
django_scientific_survey-0.3.4.dist-info/LICENSE.txt
django_scientific_survey-0.3.4.dist-info/METADATA
django_scientific_survey-0.3.4.dist-info/WHEEL
django_scientific_survey-0.3.4.dist-info/top_level.txt
django_scientific_survey-0.3.4.dist-info/RECORD
