Metadata-Version: 2.1
Name: django-scientific-survey
Version: 0.3.4
Summary: A django survey app for conducting scientific surveys, based on "django-survey-and-report" by Pierre Sassoulas.
Home-page: https://github.com/dkalpakchi/django-scientific-survey
Author: Dmytro Kalpakchi
License: AGPL
Classifier: Natural Language :: English
Classifier: Natural Language :: French
Classifier: Natural Language :: Japanese
Classifier: Natural Language :: Chinese (Traditional)
Classifier: Natural Language :: Russian
Classifier: Natural Language :: Spanish
Classifier: Natural Language :: German
Classifier: Topic :: Utilities
Classifier: Environment :: Web Environment
Classifier: Intended Audience :: Developers
Classifier: License :: OSI Approved :: GNU Affero General Public License v3
Classifier: Operating System :: OS Independent
Classifier: Programming Language :: Python :: 3.6
Classifier: Programming Language :: Python :: 3.7
Classifier: Programming Language :: Python :: 3.8
Classifier: Programming Language :: Python :: 3.9
Classifier: Programming Language :: Python :: 3.10
Classifier: Framework :: Django
License-File: LICENSE.txt
Requires-Dist: django <4,>=2.2
Requires-Dist: django-bootstrap-form >=3.4
Requires-Dist: django-registration >=3.0
Requires-Dist: django-nested-admin >=3.3.3
Requires-Dist: pytz >=2018.9
Requires-Dist: ordereddict >=1.1
Requires-Dist: pyyaml >=6.0
Requires-Dist: django-tinymce4-lite ==1.8.0
Provides-Extra: dev
Requires-Dist: django-rosetta ; extra == 'dev'
Requires-Dist: coverage ; extra == 'dev'
Requires-Dist: python-coveralls ; extra == 'dev'
Requires-Dist: coveralls ; extra == 'dev'
Requires-Dist: colorama ; extra == 'dev'
Requires-Dist: pylint ; extra == 'dev'
Requires-Dist: flake8 ; extra == 'dev'
Requires-Dist: pre-commit ; extra == 'dev'
